{"namedChunkGroups":{"polyfill":{"name":"polyfill","assets":[{"name":"webpack-runtime-a8280ee6c69daebfb4e4.js","size":5113},{"name":"polyfill-f1b1259ad4d6a43cc1c1.js","size":82198}],"filteredAssets":0,"assetsSize":87311,"filteredAuxiliaryAssets":2,"auxiliaryAssetsSize":220349},"app":{"name":"app","assets":[{"name":"webpack-runtime-a8280ee6c69daebfb4e4.js","size":5113},{"name":"styles.5d67261a6e37ed96854e.css","size":136802},{"name":"framework-93938ba4f04cca80db05.js","size":128963},{"name":"app-91314b4bb68202bdcc6f.js","size":68383}],"filteredAssets":0,"assetsSize":339261,"filteredAuxiliaryAssets":59,"auxiliaryAssetsSize":2952513},"component---src-pages-404-js":{"name":"component---src-pages-404-js","assets":[{"name":"styles.5d67261a6e37ed96854e.css","size":136802},{"name":"commons-a187cf6c5fb53694f438.js","size":16291},{"name":"component---src-pages-404-js-b97391155be0b0b9d6ef.js","size":1258}],"filteredAssets":0,"assetsSize":154351,"filteredAuxiliaryAssets":58,"auxiliaryAssetsSize":2371712},"component---src-pages-tags-js":{"name":"component---src-pages-tags-js","assets":[{"name":"styles.5d67261a6e37ed96854e.css","size":136802},{"name":"commons-a187cf6c5fb53694f438.js","size":16291},{"name":"component---src-pages-tags-js-b4fde03dfe43e0fec9c8.js","size":6265}],"filteredAssets":0,"assetsSize":159358,"filteredAuxiliaryAssets":58,"auxiliaryAssetsSize":2399005},"component---src-templates-blog-list-js":{"name":"component---src-templates-blog-list-js","assets":[{"name":"styles.5d67261a6e37ed96854e.css","size":136802},{"name":"commons-a187cf6c5fb53694f438.js","size":16291},{"name":"component---src-templates-blog-list-js-0d213925439f0354ed1f.js","size":2508}],"filteredAssets":0,"assetsSize":155601,"filteredAuxiliaryAssets":58,"auxiliaryAssetsSize":2376084},"component---src-templates-blog-post-js":{"name":"component---src-templates-blog-post-js","assets":[{"name":"styles.5d67261a6e37ed96854e.css","size":136802},{"name":"commons-a187cf6c5fb53694f438.js","size":16291},{"name":"component---src-templates-blog-post-js-4c9276a0fcfe3168aca5.js","size":7852}],"filteredAssets":0,"assetsSize":160945,"filteredAuxiliaryAssets":58,"auxiliaryAssetsSize":2404095},"component---src-templates-tags-js":{"name":"component---src-templates-tags-js","assets":[{"name":"styles.5d67261a6e37ed96854e.css","size":136802},{"name":"commons-a187cf6c5fb53694f438.js","size":16291},{"name":"component---src-templates-tags-js-5a98a4e66b783f6a248e.js","size":891}],"filteredAssets":0,"assetsSize":153984,"filteredAuxiliaryAssets":58,"auxiliaryAssetsSize":2370674}},"assetsByChunkName":{"polyfill":["webpack-runtime-a8280ee6c69daebfb4e4.js","polyfill-f1b1259ad4d6a43cc1c1.js"],"app":["webpack-runtime-a8280ee6c69daebfb4e4.js","styles.5d67261a6e37ed96854e.css","framework-93938ba4f04cca80db05.js","app-91314b4bb68202bdcc6f.js"],"component---src-pages-404-js":["styles.5d67261a6e37ed96854e.css","commons-a187cf6c5fb53694f438.js","component---src-pages-404-js-b97391155be0b0b9d6ef.js"],"component---src-pages-tags-js":["styles.5d67261a6e37ed96854e.css","commons-a187cf6c5fb53694f438.js","component---src-pages-tags-js-b4fde03dfe43e0fec9c8.js"],"component---src-templates-blog-list-js":["styles.5d67261a6e37ed96854e.css","commons-a187cf6c5fb53694f438.js","component---src-templates-blog-list-js-0d213925439f0354ed1f.js"],"component---src-templates-blog-post-js":["styles.5d67261a6e37ed96854e.css","commons-a187cf6c5fb53694f438.js","component---src-templates-blog-post-js-4c9276a0fcfe3168aca5.js"],"component---src-templates-tags-js":["styles.5d67261a6e37ed96854e.css","commons-a187cf6c5fb53694f438.js","component---src-templates-tags-js-5a98a4e66b783f6a248e.js"]},"childAssetsByChunkName":{}}